{
  "features": [
    {
      "name": "middle",
      "performance": "Good",
      "star_1": 0,
      "star_2": 0,
      "star_3": 0,
      "star_4": 3,
      "star_5": 2
    },
    {
      "name": "man",
      "performance": "Good",
      "star_1": 0,
      "star_2": 0,
      "star_3": 0,
      "star_4": 3,
      "star_5": 4
    },
    {
      "name": "cheese",
      "performance": "Good",
      "star_1": 0,
      "star_2": 0,
      "star_3": 0,
      "star_4": 3,
      "star_5": 4
    },
    {
      "name": "vegas",
      "performance": "Average",
      "star_1": 5,
      "star_2": 6,
      "star_3": 10,
      "star_4": 32,
      "star_5": 31
    },
    {
      "name": "creme fraiche",
      "performance": "Good",
      "star_1": 0,
      "star_2": 0,
      "star_3": 0,
      "star_4": 3,
      "star_5": 5
    },
    {
      "name": "tables",
      "performance": "Average",
      "star_1": 0,
      "star_2": 2,
      "star_3": 5,
      "star_4": 0,
      "star_5": 3
    },
    {
      "name": "hats",
      "performance": "Good",
      "star_1": 0,
      "star_2": 0,
      "star_3": 0,
      "star_4": 5,
      "star_5": 0
    },
    {
      "name": "chicken kiev",
      "performance": "Good",
      "star_1": 0,
      "star_2": 2,
      "star_3": 2,
      "star_4": 11,
      "star_5": 5
    },
    {
      "name": "boyfriend",
      "performance": "Good",
      "star_1": 0,
      "star_2": 0,
      "star_3": 0,
      "star_4": 3,
      "star_5": 2
    },
    {
      "name": "plan",
      "performance": "Good",
      "star_1": 0,
      "star_2": 0,
      "star_3": 0,
      "star_4": 3,
      "star_5": 2
    },
    {
      "name": "places",
      "performance": "Good",
      "star_1": 0,
      "star_2": 0,
      "star_3": 2,
      "star_4": 5,
      "star_5": 7
    },
    {
      "name": "head",
      "performance": "Good",
      "star_1": 0,
      "star_2": 0,
      "star_3": 4,
      "star_4": 9,
      "star_5": 12
    },
    {
      "name": "desert",
      "performance": "Good",
      "star_1": 0,
      "star_2": 0,
      "star_3": 0,
      "star_4": 2,
      "star_5": 3
    },
    {
      "name": "everything",
      "performance": "Good",
      "star_1": 0,
      "star_2": 0,
      "star_3": 6,
      "star_4": 7,
      "star_5": 24
    },
    {
      "name": "restaurant",
      "performance": "Average",
      "star_1": 3,
      "star_2": 8,
      "star_3": 7,
      "star_4": 17,
      "star_5": 24
    },
    {
      "name": "russia",
      "performance": "Good",
      "star_1": 0,
      "star_2": 0,
      "star_3": 0,
      "star_4": 5,
      "star_5": 7
    },
    {
      "name": "nothing",
      "performance": "Average",
      "star_1": 0,
      "star_2": 3,
      "star_3": 4,
      "star_4": 8,
      "star_5": 0
    },
    {
      "name": "bars",
      "performance": "Average",
      "star_1": 0,
      "star_2": 0,
      "star_3": 3,
      "star_4": 2,
      "star_5": 2
    },
    {
      "name": "quality",
      "performance": "Average",
      "star_1": 0,
      "star_2": 0,
      "star_3": 2,
      "star_4": 2,
      "star_5": 3
    },
    {
      "name": "cool",
      "performance": "Average",
      "star_1": 0,
      "star_2": 0,
      "star_3": 6,
      "star_4": 2,
      "star_5": 2
    },
    {
      "name": "entrees",
      "performance": "Good",
      "star_1": 0,
      "star_2": 0,
      "star_3": 0,
      "star_4": 5,
      "star_5": 5
    },
    {
      "name": "hand",
      "performance": "Good",
      "star_1": 0,
      "star_2": 0,
      "star_3": 0,
      "star_4": 3,
      "star_5": 2
    },
    {
      "name": "waitress",
      "performance": "Good",
      "star_1": 0,
      "star_2": 2,
      "star_3": 0,
      "star_4": 4,
      "star_5": 5
    },
    {
      "name": "top",
      "performance": "Good",
      "star_1": 0,
      "star_2": 0,
      "star_3": 2,
      "star_4": 3,
      "star_5": 7
    },
    {
      "name": "front",
      "performance": "Average",
      "star_1": 0,
      "star_2": 3,
      "star_3": 4,
      "star_4": 4,
      "star_5": 0
    },
    {
      "name": "flights",
      "performance": "Good",
      "star_1": 0,
      "star_2": 0,
      "star_3": 0,
      "star_4": 6,
      "star_5": 4
    },
    {
      "name": "deal",
      "performance": "Good",
      "star_1": 0,
      "star_2": 0,
      "star_3": 2,
      "star_4": 4,
      "star_5": 6
    },
    {
      "name": "tuna tartare",
      "performance": "Good",
      "star_1": 0,
      "star_2": 0,
      "star_3": 0,
      "star_4": 6,
      "star_5": 0
    },
    {
      "name": "manager",
      "performance": "Average",
      "star_1": 2,
      "star_2": 0,
      "star_3": 0,
      "star_4": 2,
      "star_5": 3
    },
    {
      "name": "items",
      "performance": "Average",
      "star_1": 0,
      "star_2": 2,
      "star_3": 0,
      "star_4": 2,
      "star_5": 2
    },
    {
      "name": "things",
      "performance": "Good",
      "star_1": 0,
      "star_2": 3,
      "star_3": 0,
      "star_4": 10,
      "star_5": 4
    },
    {
      "name": "staff",
      "performance": "Average",
      "star_1": 0,
      "star_2": 6,
      "star_3": 4,
      "star_4": 10,
      "star_5": 9
    },
    {
      "name": "bartenders",
      "performance": "Good",
      "star_1": 0,
      "star_2": 0,
      "star_3": 2,
      "star_4": 9,
      "star_5": 7
    },
    {
      "name": "sort",
      "performance": "Average",
      "star_1": 0,
      "star_2": 0,
      "star_3": 3,
      "star_4": 2,
      "star_5": 4
    },
    {
      "name": "great service",
      "performance": "Good",
      "star_1": 0,
      "star_2": 0,
      "star_3": 0,
      "star_4": 0,
      "star_5": 5
    },
    {
      "name": "waiter",
      "performance": "Average",
      "star_1": 0,
      "star_2": 2,
      "star_3": 7,
      "star_4": 8,
      "star_5": 9
    },
    {
      "name": "vault",
      "performance": "Good",
      "star_1": 0,
      "star_2": 0,
      "star_3": 0,
      "star_4": 4,
      "star_5": 3
    },
    {
      "name": "mandalay",
      "performance": "Good",
      "star_1": 0,
      "star_2": 0,
      "star_3": 0,
      "star_4": 3,
      "star_5": 4
    },
    {
      "name": "bit",
      "performance": "Good",
      "star_1": 0,
      "star_2": 0,
      "star_3": 6,
      "star_4": 12,
      "star_5": 8
    },
    {
      "name": "mouth",
      "performance": "Good",
      "star_1": 0,
      "star_2": 0,
      "star_3": 0,
      "star_4": 3,
      "star_5": 2
    },
    {
      "name": "half",
      "performance": "Average",
      "star_1": 0,
      "star_2": 0,
      "star_3": 2,
      "star_4": 3,
      "star_5": 0
    },
    {
      "name": "years",
      "performance": "Good",
      "star_1": 2,
      "star_2": 0,
      "star_3": 0,
      "star_4": 8,
      "star_5": 2
    },
    {
      "name": "shots",
      "performance": "Good",
      "star_1": 2,
      "star_2": 0,
      "star_3": 3,
      "star_4": 9,
      "star_5": 12
    },
    {
      "name": "wine",
      "performance": "Good",
      "star_1": 2,
      "star_2": 0,
      "star_3": 0,
      "star_4": 4,
      "star_5": 3
    },
    {
      "name": "year",
      "performance": "Good",
      "star_1": 0,
      "star_2": 2,
      "star_3": 0,
      "star_4": 3,
      "star_5": 6
    },
    {
      "name": "wow",
      "performance": "Good",
      "star_1": 0,
      "star_2": 0,
      "star_3": 0,
      "star_4": 2,
      "star_5": 6
    },
    {
      "name": "server",
      "performance": "Average",
      "star_1": 3,
      "star_2": 0,
      "star_3": 10,
      "star_4": 9,
      "star_5": 11
    },
    {
      "name": "group",
      "performance": "Average",
      "star_1": 0,
      "star_2": 3,
      "star_3": 4,
      "star_4": 8,
      "star_5": 5
    },
    {
      "name": "crab",
      "performance": "Good",
      "star_1": 0,
      "star_2": 0,
      "star_3": 0,
      "star_4": 0,
      "star_5": 5
    },
    {
      "name": "dish",
      "performance": "Good",
      "star_1": 0,
      "star_2": 3,
      "star_3": 0,
      "star_4": 8,
      "star_5": 2
    },
    {
      "name": "week",
      "performance": "Average",
      "star_1": 0,
      "star_2": 0,
      "star_3": 2,
      "star_4": 3,
      "star_5": 0
    },
    {
      "name": "yummy",
      "performance": "Average",
      "star_1": 0,
      "star_2": 0,
      "star_3": 2,
      "star_4": 2,
      "star_5": 4
    },
    {
      "name": "prawns",
      "performance": "Good",
      "star_1": 0,
      "star_2": 0,
      "star_3": 0,
      "star_4": 2,
      "star_5": 3
    },
    {
      "name": "menu",
      "performance": "Average",
      "star_1": 2,
      "star_2": 5,
      "star_3": 8,
      "star_4": 18,
      "star_5": 21
    },
    {
      "name": "ice",
      "performance": "Good",
      "star_1": 0,
      "star_2": 0,
      "star_3": 2,
      "star_4": 15,
      "star_5": 15
    },
    {
      "name": "potatoes",
      "performance": "Good",
      "star_1": 0,
      "star_2": 0,
      "star_3": 0,
      "star_4": 5,
      "star_5": 2
    },
    {
      "name": "hours",
      "performance": "Bad",
      "star_1": 3,
      "star_2": 2,
      "star_3": 0,
      "star_4": 4,
      "star_5": 0
    },
    {
      "name": "mary",
      "performance": "Average",
      "star_1": 0,
      "star_2": 0,
      "star_3": 2,
      "star_4": 2,
      "star_5": 3
    },
    {
      "name": "dinner",
      "performance": "Average",
      "star_1": 0,
      "star_2": 0,
      "star_3": 18,
      "star_4": 25,
      "star_5": 20
    },
    {
      "name": "dishes",
      "performance": "Average",
      "star_1": 0,
      "star_2": 3,
      "star_3": 3,
      "star_4": 8,
      "star_5": 2
    },
    {
      "name": "life",
      "performance": "Good",
      "star_1": 0,
      "star_2": 0,
      "star_3": 0,
      "star_4": 2,
      "star_5": 3
    },
    {
      "name": "everyone",
      "performance": "Average",
      "star_1": 2,
      "star_2": 2,
      "star_3": 0,
      "star_4": 3,
      "star_5": 2
    },
    {
      "name": "couple",
      "performance": "Good",
      "star_1": 0,
      "star_2": 0,
      "star_3": 3,
      "star_4": 8,
      "star_5": 4
    },
    {
      "name": "lobster bisque",
      "performance": "Good",
      "star_1": 0,
      "star_2": 0,
      "star_3": 0,
      "star_4": 4,
      "star_5": 2
    },
    {
      "name": "dessert",
      "performance": "Good",
      "star_1": 0,
      "star_2": 2,
      "star_3": 4,
      "star_4": 10,
      "star_5": 9
    },
    {
      "name": "chernobyl",
      "performance": "Good",
      "star_1": 0,
      "star_2": 0,
      "star_3": 0,
      "star_4": 3,
      "star_5": 6
    },
    {
      "name": "course",
      "performance": "Good",
      "star_1": 0,
      "star_2": 0,
      "star_3": 2,
      "star_4": 5,
      "star_5": 8
    },
    {
      "name": "water",
      "performance": "Good",
      "star_1": 0,
      "star_2": 0,
      "star_3": 0,
      "star_4": 2,
      "star_5": 3
    },
    {
      "name": "party",
      "performance": "Average",
      "star_1": 0,
      "star_2": 0,
      "star_3": 3,
      "star_4": 3,
      "star_5": 3
    },
    {
      "name": "house",
      "performance": "Average",
      "star_1": 0,
      "star_2": 0,
      "star_3": 2,
      "star_4": 4,
      "star_5": 2
    },
    {
      "name": "noodles",
      "performance": "Bad",
      "star_1": 0,
      "star_2": 3,
      "star_3": 0,
      "star_4": 3,
      "star_5": 0
    },
    {
      "name": "stalin",
      "performance": "Good",
      "star_1": 0,
      "star_2": 0,
      "star_3": 0,
      "star_4": 3,
      "star_5": 3
    },
    {
      "name": "decor",
      "performance": "Good",
      "star_1": 0,
      "star_2": 2,
      "star_3": 9,
      "star_4": 24,
      "star_5": 19
    },
    {
      "name": "way",
      "performance": "Average",
      "star_1": 3,
      "star_2": 2,
      "star_3": 6,
      "star_4": 17,
      "star_5": 11
    },
    {
      "name": "roquefort filet mignon",
      "performance": "Good",
      "star_1": 0,
      "star_2": 0,
      "star_3": 0,
      "star_4": 3,
      "star_5": 2
    },
    {
      "name": "drinks",
      "performance": "Average",
      "star_1": 3,
      "star_2": 14,
      "star_3": 18,
      "star_4": 53,
      "star_5": 47
    },
    {
      "name": "vodka selection",
      "performance": "Good",
      "star_1": 0,
      "star_2": 0,
      "star_3": 0,
      "star_4": 2,
      "star_5": 3
    },
    {
      "name": "espresso martini",
      "performance": "Good",
      "star_1": 0,
      "star_2": 0,
      "star_3": 0,
      "star_4": 2,
      "star_5": 3
    },
    {
      "name": "table",
      "performance": "Good",
      "star_1": 0,
      "star_2": 0,
      "star_3": 6,
      "star_4": 14,
      "star_5": 5
    },
    {
      "name": "apps",
      "performance": "Average",
      "star_1": 0,
      "star_2": 0,
      "star_3": 2,
      "star_4": 0,
      "star_5": 4
    },
    {
      "name": "home",
      "performance": "Average",
      "star_1": 0,
      "star_2": 2,
      "star_3": 4,
      "star_4": 4,
      "star_5": 3
    },
    {
      "name": "star",
      "performance": "Good",
      "star_1": 0,
      "star_2": 2,
      "star_3": 0,
      "star_4": 6,
      "star_5": 2
    },
    {
      "name": "lighting",
      "performance": "Good",
      "star_1": 0,
      "star_2": 0,
      "star_3": 2,
      "star_4": 6,
      "star_5": 8
    },
    {
      "name": "chicken",
      "performance": "Good",
      "star_1": 0,
      "star_2": 0,
      "star_3": 0,
      "star_4": 5,
      "star_5": 2
    },
    {
      "name": "anyone",
      "performance": "Good",
      "star_1": 0,
      "star_2": 0,
      "star_3": 0,
      "star_4": 5,
      "star_5": 3
    },
    {
      "name": "something",
      "performance": "Good",
      "star_1": 0,
      "star_2": 0,
      "star_3": 6,
      "star_4": 15,
      "star_5": 10
    },
    {
      "name": "food",
      "performance": "Average",
      "star_1": 6,
      "star_2": 14,
      "star_3": 23,
      "star_4": 62,
      "star_5": 51
    },
    {
      "name": "music",
      "performance": "Average",
      "star_1": 0,
      "star_2": 0,
      "star_3": 2,
      "star_4": 3,
      "star_5": 0
    },
    {
      "name": "plenty",
      "performance": "Average",
      "star_1": 0,
      "star_2": 0,
      "star_3": 2,
      "star_4": 3,
      "star_5": 0
    },
    {
      "name": "vegas trip",
      "performance": "Good",
      "star_1": 0,
      "star_2": 0,
      "star_3": 0,
      "star_4": 2,
      "star_5": 3
    },
    {
      "name": "salmon",
      "performance": "Good",
      "star_1": 0,
      "star_2": 0,
      "star_3": 4,
      "star_4": 9,
      "star_5": 12
    },
    {
      "name": "lobster",
      "performance": "Good",
      "star_1": 0,
      "star_2": 0,
      "star_3": 2,
      "star_4": 3,
      "star_5": 4
    },
    {
      "name": "fact",
      "performance": "Average",
      "star_1": 0,
      "star_2": 0,
      "star_3": 3,
      "star_4": 3,
      "star_5": 3
    },
    {
      "name": "round",
      "performance": "Good",
      "star_1": 0,
      "star_2": 0,
      "star_3": 0,
      "star_4": 5,
      "star_5": 2
    },
    {
      "name": "square",
      "performance": "Good",
      "star_1": 0,
      "star_2": 0,
      "star_3": 2,
      "star_4": 3,
      "star_5": 11
    },
    {
      "name": "ice bar",
      "performance": "Good",
      "star_1": 0,
      "star_2": 0,
      "star_3": 3,
      "star_4": 13,
      "star_5": 19
    },
    {
      "name": "bar made",
      "performance": "Good",
      "star_1": 0,
      "star_2": 0,
      "star_3": 0,
      "star_4": 2,
      "star_5": 3
    },
    {
      "name": "try",
      "performance": "Good",
      "star_1": 0,
      "star_2": 0,
      "star_3": 0,
      "star_4": 2,
      "star_5": 3
    },
    {
      "name": "complaint",
      "performance": "Good",
      "star_1": 0,
      "star_2": 0,
      "star_3": 0,
      "star_4": 4,
      "star_5": 2
    },
    {
      "name": "ambience",
      "performance": "Average",
      "star_1": 0,
      "star_2": 0,
      "star_3": 2,
      "star_4": 2,
      "star_5": 2
    },
    {
      "name": "mood",
      "performance": "Good",
      "star_1": 0,
      "star_2": 0,
      "star_3": 0,
      "star_4": 5,
      "star_5": 3
    },
    {
      "name": "glasses",
      "performance": "Good",
      "star_1": 0,
      "star_2": 0,
      "star_3": 0,
      "star_4": 5,
      "star_5": 0
    },
    {
      "name": "reason",
      "performance": "Average",
      "star_1": 2,
      "star_2": 0,
      "star_3": 0,
      "star_4": 6,
      "star_5": 0
    },
    {
      "name": "place",
      "performance": "Average",
      "star_1": 7,
      "star_2": 11,
      "star_3": 20,
      "star_4": 58,
      "star_5": 55
    },
    {
      "name": "dim",
      "performance": "Good",
      "star_1": 0,
      "star_2": 0,
      "star_3": 0,
      "star_4": 2,
      "star_5": 4
    },
    {
      "name": "one",
      "performance": "Average",
      "star_1": 0,
      "star_2": 0,
      "star_3": 2,
      "star_4": 5,
      "star_5": 0
    },
    {
      "name": "door",
      "performance": "Average",
      "star_1": 3,
      "star_2": 2,
      "star_3": 3,
      "star_4": 3,
      "star_5": 4
    },
    {
      "name": "bottle",
      "performance": "Average",
      "star_1": 0,
      "star_2": 0,
      "star_3": 5,
      "star_4": 11,
      "star_5": 3
    },
    {
      "name": "size",
      "performance": "Average",
      "star_1": 0,
      "star_2": 0,
      "star_3": 2,
      "star_4": 3,
      "star_5": 0
    },
    {
      "name": "anything",
      "performance": "Average",
      "star_1": 2,
      "star_2": 6,
      "star_3": 3,
      "star_4": 2,
      "star_5": 6
    },
    {
      "name": "rare",
      "performance": "Average",
      "star_1": 0,
      "star_2": 0,
      "star_3": 3,
      "star_4": 0,
      "star_5": 2
    },
    {
      "name": "friends",
      "performance": "Good",
      "star_1": 0,
      "star_2": 2,
      "star_3": 2,
      "star_4": 10,
      "star_5": 13
    },
    {
      "name": "night",
      "performance": "Good",
      "star_1": 0,
      "star_2": 3,
      "star_3": 5,
      "star_4": 17,
      "star_5": 14
    },
    {
      "name": "dollars",
      "performance": "Average",
      "star_1": 2,
      "star_2": 0,
      "star_3": 2,
      "star_4": 0,
      "star_5": 3
    },
    {
      "name": "nachos",
      "performance": "Good",
      "star_1": 0,
      "star_2": 0,
      "star_3": 7,
      "star_4": 12,
      "star_5": 10
    },
    {
      "name": "love",
      "performance": "Good",
      "star_1": 0,
      "star_2": 0,
      "star_3": 0,
      "star_4": 6,
      "star_5": 3
    },
    {
      "name": "wife",
      "performance": "Average",
      "star_1": 0,
      "star_2": 0,
      "star_3": 3,
      "star_4": 4,
      "star_5": 3
    },
    {
      "name": "tasting menu",
      "performance": "Average",
      "star_1": 0,
      "star_2": 0,
      "star_3": 2,
      "star_4": 3,
      "star_5": 0
    },
    {
      "name": "vodkas",
      "performance": "Good",
      "star_1": 0,
      "star_2": 2,
      "star_3": 6,
      "star_4": 15,
      "star_5": 14
    },
    {
      "name": "caviar",
      "performance": "Good",
      "star_1": 0,
      "star_2": 2,
      "star_3": 7,
      "star_4": 14,
      "star_5": 16
    },
    {
      "name": "friend",
      "performance": "Average",
      "star_1": 0,
      "star_2": 4,
      "star_3": 8,
      "star_4": 8,
      "star_5": 11
    },
    {
      "name": "came",
      "performance": "Good",
      "star_1": 0,
      "star_2": 0,
      "star_3": 0,
      "star_4": 5,
      "star_5": 2
    },
    {
      "name": "mandalay bay",
      "performance": "Average",
      "star_1": 6,
      "star_2": 2,
      "star_3": 4,
      "star_4": 21,
      "star_5": 15
    },
    {
      "name": "husband",
      "performance": "Good",
      "star_1": 0,
      "star_2": 0,
      "star_3": 2,
      "star_4": 8,
      "star_5": 7
    },
    {
      "name": "someone",
      "performance": "Average",
      "star_1": 2,
      "star_2": 0,
      "star_3": 3,
      "star_4": 3,
      "star_5": 4
    },
    {
      "name": "fries",
      "performance": "Good",
      "star_1": 0,
      "star_2": 0,
      "star_3": 0,
      "star_4": 3,
      "star_5": 3
    },
    {
      "name": "liquor",
      "performance": "Good",
      "star_1": 0,
      "star_2": 0,
      "star_3": 0,
      "star_4": 3,
      "star_5": 3
    },
    {
      "name": "show",
      "performance": "Good",
      "star_1": 0,
      "star_2": 0,
      "star_3": 0,
      "star_4": 2,
      "star_5": 3
    },
    {
      "name": "day",
      "performance": "Good",
      "star_1": 0,
      "star_2": 0,
      "star_3": 4,
      "star_4": 12,
      "star_5": 5
    },
    {
      "name": "bartender",
      "performance": "Good",
      "star_1": 2,
      "star_2": 0,
      "star_3": 3,
      "star_4": 11,
      "star_5": 10
    },
    {
      "name": "beef",
      "performance": "Average",
      "star_1": 0,
      "star_2": 2,
      "star_3": 3,
      "star_4": 5,
      "star_5": 2
    },
    {
      "name": "pasta",
      "performance": "Average",
      "star_1": 0,
      "star_2": 0,
      "star_3": 2,
      "star_4": 2,
      "star_5": 2
    },
    {
      "name": "cocktails",
      "performance": "Average",
      "star_1": 2,
      "star_2": 0,
      "star_3": 8,
      "star_4": 15,
      "star_5": 13
    },
    {
      "name": "visits",
      "performance": "Good",
      "star_1": 0,
      "star_2": 0,
      "star_3": 0,
      "star_4": 2,
      "star_5": 3
    },
    {
      "name": "weekend",
      "performance": "Average",
      "star_1": 0,
      "star_2": 0,
      "star_3": 2,
      "star_4": 0,
      "star_5": 4
    },
    {
      "name": "selection",
      "performance": "Good",
      "star_1": 0,
      "star_2": 0,
      "star_3": 4,
      "star_4": 15,
      "star_5": 6
    },
    {
      "name": "interior",
      "performance": "Good",
      "star_1": 0,
      "star_2": 0,
      "star_3": 0,
      "star_4": 6,
      "star_5": 0
    },
    {
      "name": "come",
      "performance": "Average",
      "star_1": 0,
      "star_2": 0,
      "star_3": 3,
      "star_4": 2,
      "star_5": 0
    },
    {
      "name": "money",
      "performance": "Average",
      "star_1": 4,
      "star_2": 4,
      "star_3": 3,
      "star_4": 5,
      "star_5": 5
    },
    {
      "name": "sliders",
      "performance": "Good",
      "star_1": 0,
      "star_2": 2,
      "star_3": 0,
      "star_4": 4,
      "star_5": 6
    },
    {
      "name": "vodka",
      "performance": "Average",
      "star_1": 2,
      "star_2": 5,
      "star_3": 8,
      "star_4": 23,
      "star_5": 21
    },
    {
      "name": "point",
      "performance": "Good",
      "star_1": 0,
      "star_2": 2,
      "star_3": 0,
      "star_4": 5,
      "star_5": 5
    },
    {
      "name": "salad",
      "performance": "Good",
      "star_1": 0,
      "star_2": 0,
      "star_3": 3,
      "star_4": 4,
      "star_5": 6
    },
    {
      "name": "vodka bar",
      "performance": "Average",
      "star_1": 0,
      "star_2": 0,
      "star_3": 3,
      "star_4": 3,
      "star_5": 2
    },
    {
      "name": "visit",
      "performance": "Good",
      "star_1": 0,
      "star_2": 0,
      "star_3": 2,
      "star_4": 5,
      "star_5": 5
    },
    {
      "name": "stars",
      "performance": "Average",
      "star_1": 0,
      "star_2": 3,
      "star_3": 5,
      "star_4": 12,
      "star_5": 5
    },
    {
      "name": "rest",
      "performance": "Average",
      "star_1": 0,
      "star_2": 2,
      "star_3": 2,
      "star_4": 0,
      "star_5": 2
    },
    {
      "name": "martini",
      "performance": "Average",
      "star_1": 2,
      "star_2": 0,
      "star_3": 8,
      "star_4": 9,
      "star_5": 10
    },
    {
      "name": "list",
      "performance": "Good",
      "star_1": 0,
      "star_2": 0,
      "star_3": 0,
      "star_4": 8,
      "star_5": 4
    },
    {
      "name": "lol",
      "performance": "Good",
      "star_1": 0,
      "star_2": 0,
      "star_3": 0,
      "star_4": 2,
      "star_5": 3
    },
    {
      "name": "steak",
      "performance": "Average",
      "star_1": 3,
      "star_2": 3,
      "star_3": 5,
      "star_4": 5,
      "star_5": 10
    },
    {
      "name": "person",
      "performance": "Good",
      "star_1": 0,
      "star_2": 0,
      "star_3": 0,
      "star_4": 5,
      "star_5": 2
    },
    {
      "name": "entree",
      "performance": "Average",
      "star_1": 0,
      "star_2": 0,
      "star_3": 4,
      "star_4": 5,
      "star_5": 2
    },
    {
      "name": "meat",
      "performance": "Average",
      "star_1": 0,
      "star_2": 3,
      "star_3": 3,
      "star_4": 0,
      "star_5": 3
    },
    {
      "name": "hostess",
      "performance": "Good",
      "star_1": 0,
      "star_2": 0,
      "star_3": 2,
      "star_4": 3,
      "star_5": 4
    },
    {
      "name": "red square",
      "performance": "Average",
      "star_1": 8,
      "star_2": 5,
      "star_3": 18,
      "star_4": 40,
      "star_5": 33
    },
    {
      "name": "price",
      "performance": "Average",
      "star_1": 2,
      "star_2": 0,
      "star_3": 3,
      "star_4": 8,
      "star_5": 4
    },
    {
      "name": "world",
      "performance": "Good",
      "star_1": 0,
      "star_2": 0,
      "star_3": 0,
      "star_4": 3,
      "star_5": 7
    },
    {
      "name": "end",
      "performance": "Good",
      "star_1": 0,
      "star_2": 3,
      "star_3": 0,
      "star_4": 5,
      "star_5": 8
    },
    {
      "name": "stroganoff",
      "performance": "Average",
      "star_1": 2,
      "star_2": 4,
      "star_3": 3,
      "star_4": 17,
      "star_5": 5
    },
    {
      "name": "evening",
      "performance": "Good",
      "star_1": 0,
      "star_2": 0,
      "star_3": 0,
      "star_4": 4,
      "star_5": 7
    },
    {
      "name": "share",
      "performance": "Good",
      "star_1": 0,
      "star_2": 0,
      "star_3": 0,
      "star_4": 5,
      "star_5": 3
    },
    {
      "name": "steak tartare",
      "performance": "Good",
      "star_1": 0,
      "star_2": 0,
      "star_3": 0,
      "star_4": 5,
      "star_5": 2
    },
    {
      "name": "meal",
      "performance": "Average",
      "star_1": 0,
      "star_2": 0,
      "star_3": 7,
      "star_4": 10,
      "star_5": 11
    },
    {
      "name": "just",
      "performance": "Good",
      "star_1": 0,
      "star_2": 0,
      "star_3": 0,
      "star_4": 4,
      "star_5": 2
    },
    {
      "name": "fun",
      "performance": "Average",
      "star_1": 0,
      "star_2": 0,
      "star_3": 7,
      "star_4": 7,
      "star_5": 2
    },
    {
      "name": "service",
      "performance": "Average",
      "star_1": 2,
      "star_2": 12,
      "star_3": 23,
      "star_4": 31,
      "star_5": 28
    },
    {
      "name": "strip",
      "performance": "Good",
      "star_1": 0,
      "star_2": 0,
      "star_3": 0,
      "star_4": 9,
      "star_5": 8
    },
    {
      "name": "seat",
      "performance": "Good",
      "star_1": 0,
      "star_2": 0,
      "star_3": 0,
      "star_4": 2,
      "star_5": 3
    },
    {
      "name": "lots",
      "performance": "Good",
      "star_1": 0,
      "star_2": 0,
      "star_3": 3,
      "star_4": 7,
      "star_5": 4
    },
    {
      "name": "filet",
      "performance": "Good",
      "star_1": 0,
      "star_2": 0,
      "star_3": 0,
      "star_4": 5,
      "star_5": 3
    },
    {
      "name": "order",
      "performance": "Average",
      "star_1": 2,
      "star_2": 2,
      "star_3": 5,
      "star_4": 8,
      "star_5": 12
    },
    {
      "name": "fan",
      "performance": "Good",
      "star_1": 0,
      "star_2": 0,
      "star_3": 2,
      "star_4": 6,
      "star_5": 2
    },
    {
      "name": "light",
      "performance": "Good",
      "star_1": 0,
      "star_2": 0,
      "star_3": 0,
      "star_4": 2,
      "star_5": 3
    },
    {
      "name": "asparagus",
      "performance": "Average",
      "star_1": 0,
      "star_2": 0,
      "star_3": 3,
      "star_4": 4,
      "star_5": 2
    },
    {
      "name": "i",
      "performance": "Good",
      "star_1": 0,
      "star_2": 0,
      "star_3": 0,
      "star_4": 4,
      "star_5": 4
    },
    {
      "name": "lot",
      "performance": "Average",
      "star_1": 0,
      "star_2": 0,
      "star_3": 7,
      "star_4": 7,
      "star_5": 9
    },
    {
      "name": "piece",
      "performance": "Average",
      "star_1": 0,
      "star_2": 0,
      "star_3": 2,
      "star_4": 2,
      "star_5": 2
    },
    {
      "name": "idea",
      "performance": "Good",
      "star_1": 0,
      "star_2": 0,
      "star_3": 0,
      "star_4": 5,
      "star_5": 3
    },
    {
      "name": "coats",
      "performance": "Good",
      "star_1": 0,
      "star_2": 0,
      "star_3": 0,
      "star_4": 5,
      "star_5": 5
    },
    {
      "name": "reservation",
      "performance": "Good",
      "star_1": 0,
      "star_2": 0,
      "star_3": 0,
      "star_4": 3,
      "star_5": 6
    },
    {
      "name": "hour",
      "performance": "Good",
      "star_1": 4,
      "star_2": 2,
      "star_3": 2,
      "star_4": 17,
      "star_5": 13
    },
    {
      "name": "restaurants",
      "performance": "Average",
      "star_1": 0,
      "star_2": 3,
      "star_3": 3,
      "star_4": 6,
      "star_5": 6
    },
    {
      "name": "bottles",
      "performance": "Good",
      "star_1": 0,
      "star_2": 0,
      "star_3": 0,
      "star_4": 8,
      "star_5": 2
    },
    {
      "name": "guy",
      "performance": "Average",
      "star_1": 0,
      "star_2": 0,
      "star_3": 3,
      "star_4": 2,
      "star_5": 3
    },
    {
      "name": "time",
      "performance": "Average",
      "star_1": 5,
      "star_2": 7,
      "star_3": 17,
      "star_4": 31,
      "star_5": 42
    },
    {
      "name": "choice",
      "performance": "Good",
      "star_1": 0,
      "star_2": 0,
      "star_3": 0,
      "star_4": 6,
      "star_5": 3
    },
    {
      "name": "experience",
      "performance": "Average",
      "star_1": 2,
      "star_2": 7,
      "star_3": 10,
      "star_4": 17,
      "star_5": 18
    },
    {
      "name": "statue",
      "performance": "Average",
      "star_1": 0,
      "star_2": 0,
      "star_3": 5,
      "star_4": 5,
      "star_5": 3
    },
    {
      "name": "moscow mule",
      "performance": "Good",
      "star_1": 0,
      "star_2": 2,
      "star_3": 0,
      "star_4": 7,
      "star_5": 4
    },
    {
      "name": "atmosphere",
      "performance": "Average",
      "star_1": 0,
      "star_2": 5,
      "star_3": 7,
      "star_4": 16,
      "star_5": 13
    },
    {
      "name": "trip",
      "performance": "Good",
      "star_1": 0,
      "star_2": 0,
      "star_3": 0,
      "star_4": 7,
      "star_5": 10
    },
    {
      "name": "thing",
      "performance": "Average",
      "star_1": 0,
      "star_2": 3,
      "star_3": 4,
      "star_4": 14,
      "star_5": 6
    },
    {
      "name": "onions",
      "performance": "Good",
      "star_1": 0,
      "star_2": 0,
      "star_3": 0,
      "star_4": 3,
      "star_5": 3
    },
    {
      "name": "flavor",
      "performance": "Average",
      "star_1": 0,
      "star_2": 0,
      "star_3": 5,
      "star_4": 7,
      "star_5": 5
    },
    {
      "name": "freezer",
      "performance": "Average",
      "star_1": 0,
      "star_2": 0,
      "star_3": 3,
      "star_4": 6,
      "star_5": 3
    },
    {
      "name": "hotel",
      "performance": "Average",
      "star_1": 0,
      "star_2": 0,
      "star_3": 2,
      "star_4": 2,
      "star_5": 4
    },
    {
      "name": "afternoon",
      "performance": "Average",
      "star_1": 0,
      "star_2": 0,
      "star_3": 2,
      "star_4": 0,
      "star_5": 3
    },
    {
      "name": "problem",
      "performance": "Good",
      "star_1": 0,
      "star_2": 0,
      "star_3": 0,
      "star_4": 3,
      "star_5": 2
    },
    {
      "name": "foie gras",
      "performance": "Average",
      "star_1": 0,
      "star_2": 0,
      "star_3": 2,
      "star_4": 0,
      "star_5": 3
    },
    {
      "name": "perfection",
      "performance": "Good",
      "star_1": 0,
      "star_2": 0,
      "star_3": 0,
      "star_4": 2,
      "star_5": 4
    },
    {
      "name": "words",
      "performance": "Good",
      "star_1": 0,
      "star_2": 0,
      "star_3": 0,
      "star_4": 2,
      "star_5": 3
    },
    {
      "name": "times",
      "performance": "Average",
      "star_1": 0,
      "star_2": 3,
      "star_3": 3,
      "star_4": 7,
      "star_5": 10
    },
    {
      "name": "taste",
      "performance": "Average",
      "star_1": 0,
      "star_2": 4,
      "star_3": 0,
      "star_4": 7,
      "star_5": 2
    },
    {
      "name": "town",
      "performance": "Good",
      "star_1": 0,
      "star_2": 0,
      "star_3": 0,
      "star_4": 6,
      "star_5": 5
    },
    {
      "name": "opinion",
      "performance": "Good",
      "star_1": 0,
      "star_2": 0,
      "star_3": 0,
      "star_4": 4,
      "star_5": 2
    },
    {
      "name": "side",
      "performance": "Average",
      "star_1": 0,
      "star_2": 2,
      "star_3": 5,
      "star_4": 9,
      "star_5": 3
    },
    {
      "name": "filet mignon",
      "performance": "Good",
      "star_1": 0,
      "star_2": 0,
      "star_3": 3,
      "star_4": 7,
      "star_5": 4
    },
    {
      "name": "filet oscar",
      "performance": "Average",
      "star_1": 0,
      "star_2": 0,
      "star_3": 2,
      "star_4": 0,
      "star_5": 3
    },
    {
      "name": "pricey",
      "performance": "Good",
      "star_1": 0,
      "star_2": 0,
      "star_3": 2,
      "star_4": 4,
      "star_5": 3
    },
    {
      "name": "part",
      "performance": "Average",
      "star_1": 0,
      "star_2": 0,
      "star_3": 3,
      "star_4": 3,
      "star_5": 4
    },
    {
      "name": "days",
      "performance": "Average",
      "star_1": 0,
      "star_2": 0,
      "star_3": 3,
      "star_4": 0,
      "star_5": 2
    },
    {
      "name": "walls",
      "performance": "Good",
      "star_1": 0,
      "star_2": 0,
      "star_3": 0,
      "star_4": 4,
      "star_5": 2
    },
    {
      "name": "block",
      "performance": "Good",
      "star_1": 0,
      "star_2": 0,
      "star_3": 0,
      "star_4": 5,
      "star_5": 2
    },
    {
      "name": "bill",
      "performance": "Good",
      "star_1": 2,
      "star_2": 0,
      "star_3": 0,
      "star_4": 6,
      "star_5": 4
    },
    {
      "name": "people",
      "performance": "Average",
      "star_1": 4,
      "star_2": 5,
      "star_3": 6,
      "star_4": 9,
      "star_5": 10
    },
    {
      "name": "review",
      "performance": "Average",
      "star_1": 2,
      "star_2": 2,
      "star_3": 2,
      "star_4": 4,
      "star_5": 6
    },
    {
      "name": "presentation",
      "performance": "Average",
      "star_1": 0,
      "star_2": 0,
      "star_3": 2,
      "star_4": 0,
      "star_5": 3
    },
    {
      "name": "space",
      "performance": "Average",
      "star_1": 0,
      "star_2": 0,
      "star_3": 3,
      "star_4": 0,
      "star_5": 3
    },
    {
      "name": "spot",
      "performance": "Average",
      "star_1": 0,
      "star_2": 0,
      "star_3": 4,
      "star_4": 2,
      "star_5": 7
    },
    {
      "name": "glass",
      "performance": "Good",
      "star_1": 0,
      "star_2": 0,
      "star_3": 0,
      "star_4": 5,
      "star_5": 2
    },
    {
      "name": "flight",
      "performance": "Good",
      "star_1": 0,
      "star_2": 0,
      "star_3": 2,
      "star_4": 5,
      "star_5": 3
    },
    {
      "name": "lenin",
      "performance": "Average",
      "star_1": 0,
      "star_2": 0,
      "star_3": 5,
      "star_4": 8,
      "star_5": 7
    },
    {
      "name": "touch",
      "performance": "Good",
      "star_1": 0,
      "star_2": 0,
      "star_3": 0,
      "star_4": 3,
      "star_5": 4
    },
    {
      "name": "appetizers",
      "performance": "Good",
      "star_1": 0,
      "star_2": 2,
      "star_3": 4,
      "star_4": 15,
      "star_5": 10
    },
    {
      "name": "prices",
      "performance": "Average",
      "star_1": 0,
      "star_2": 0,
      "star_3": 5,
      "star_4": 11,
      "star_5": 3
    },
    {
      "name": "vodka flights",
      "performance": "Good",
      "star_1": 0,
      "star_2": 0,
      "star_3": 0,
      "star_4": 2,
      "star_5": 5
    },
    {
      "name": "cocktail",
      "performance": "Average",
      "star_1": 0,
      "star_2": 0,
      "star_3": 3,
      "star_4": 4,
      "star_5": 2
    },
    {
      "name": "calamari",
      "performance": "Average",
      "star_1": 2,
      "star_2": 0,
      "star_3": 3,
      "star_4": 6,
      "star_5": 5
    },
    {
      "name": "bar",
      "performance": "Average",
      "star_1": 4,
      "star_2": 4,
      "star_3": 18,
      "star_4": 30,
      "star_5": 32
    },
    {
      "name": "portions",
      "performance": "Good",
      "star_1": 0,
      "star_2": 2,
      "star_3": 0,
      "star_4": 8,
      "star_5": 2
    },
    {
      "name": "appetizer",
      "performance": "Average",
      "star_1": 0,
      "star_2": 0,
      "star_3": 6,
      "star_4": 3,
      "star_5": 9
    },
    {
      "name": "room",
      "performance": "Average",
      "star_1": 0,
      "star_2": 3,
      "star_3": 4,
      "star_4": 8,
      "star_5": 2
    },
    {
      "name": "casino",
      "performance": "Good",
      "star_1": 0,
      "star_2": 0,
      "star_3": 0,
      "star_4": 3,
      "star_5": 3
    },
    {
      "name": "tasty",
      "performance": "Good",
      "star_1": 0,
      "star_2": 0,
      "star_3": 0,
      "star_4": 2,
      "star_5": 3
    },
    {
      "name": "plate",
      "performance": "Good",
      "star_1": 0,
      "star_2": 0,
      "star_3": 0,
      "star_4": 3,
      "star_5": 4
    },
    {
      "name": "theme",
      "performance": "Good",
      "star_1": 0,
      "star_2": 0,
      "star_3": 2,
      "star_4": 5,
      "star_5": 6
    },
    {
      "name": "shot",
      "performance": "Average",
      "star_1": 0,
      "star_2": 0,
      "star_3": 3,
      "star_4": 3,
      "star_5": 5
    },
    {
      "name": "ask",
      "performance": "Good",
      "star_1": 0,
      "star_2": 0,
      "star_3": 0,
      "star_4": 2,
      "star_5": 4
    },
    {
      "name": "others",
      "performance": "Good",
      "star_1": 0,
      "star_2": 0,
      "star_3": 0,
      "star_4": 3,
      "star_5": 4
    },
    {
      "name": "sauce",
      "performance": "Average",
      "star_1": 0,
      "star_2": 3,
      "star_3": 4,
      "star_4": 5,
      "star_5": 4
    },
    {
      "name": "minutes",
      "performance": "Bad",
      "star_1": 0,
      "star_2": 3,
      "star_3": 0,
      "star_4": 0,
      "star_5": 2
    },
    {
      "name": "ambiance",
      "performance": "Average",
      "star_1": 0,
      "star_2": 0,
      "star_3": 9,
      "star_4": 11,
      "star_5": 9
    },
    {
      "name": "vodka vault",
      "performance": "Good",
      "star_1": 0,
      "star_2": 0,
      "star_3": 4,
      "star_4": 10,
      "star_5": 7
    },
    {
      "name": "name",
      "performance": "Average",
      "star_1": 0,
      "star_2": 2,
      "star_3": 3,
      "star_4": 6,
      "star_5": 4
    },
    {
      "name": "martinis",
      "performance": "Good",
      "star_1": 0,
      "star_2": 0,
      "star_3": 0,
      "star_4": 15,
      "star_5": 16
    },
    {
      "name": "kind",
      "performance": "Good",
      "star_1": 0,
      "star_2": 0,
      "star_3": 6,
      "star_4": 9,
      "star_5": 12
    },
    {
      "name": "beef stroganoff",
      "performance": "Average",
      "star_1": 0,
      "star_2": 2,
      "star_3": 3,
      "star_4": 9,
      "star_5": 5
    },
    {
      "name": "vodka flight",
      "performance": "Good",
      "star_1": 0,
      "star_2": 0,
      "star_3": 0,
      "star_4": 3,
      "star_5": 4
    },
    {
      "name": "meatballs",
      "performance": "Good",
      "star_1": 0,
      "star_2": 0,
      "star_3": 0,
      "star_4": 4,
      "star_5": 4
    },
    {
      "name": "bar top",
      "performance": "Good",
      "star_1": 0,
      "star_2": 0,
      "star_3": 0,
      "star_4": 4,
      "star_5": 3
    },
    {
      "name": "great",
      "performance": "Good",
      "star_1": 0,
      "star_2": 0,
      "star_3": 0,
      "star_4": 3,
      "star_5": 2
    },
    {
      "name": "las vegas",
      "performance": "Average",
      "star_1": 4,
      "star_2": 2,
      "star_3": 2,
      "star_4": 7,
      "star_5": 13
    },
    {
      "name": "drink",
      "performance": "Average",
      "star_1": 2,
      "star_2": 3,
      "star_3": 11,
      "star_4": 22,
      "star_5": 25
    },
    {
      "name": "risotto",
      "performance": "Good",
      "star_1": 0,
      "star_2": 0,
      "star_3": 0,
      "star_4": 4,
      "star_5": 2
    },
    {
      "name": "salt",
      "performance": "Average",
      "star_1": 0,
      "star_2": 0,
      "star_3": 3,
      "star_4": 2,
      "star_5": 0
    }
  ]
}